{"config":{"output_file":null,"full_docs":false,"pub_only":true,"reachable_only":true,"distro_crate":false,"signatures":false,"borrow_data":false},"version":"0.18.2","compilation":{"directory":[47,85,115,101,114,115,47,107,97,102,117,104,97,109,97,100,97,47,46,99,97,114,103,111,47,114,101,103,105,115,116,114,121,47,115,114,99,47,103,105,116,104,117,98,46,99,111,109,45,49,101,99,99,54,50,57,57,100,98,57,101,99,56,50,51,47,114,101,115,111,108,118,45,99,111,110,102,45,48,46,54,46,50],"program":"/Users/kafuhamada/.rustup/toolchains/stable-x86_64-apple-darwin/bin/rls","arguments":["--crate-name","resolv_conf","/Users/kafuhamada/.cargo/registry/src/github.com-1ecc6299db9ec823/resolv-conf-0.6.2/src/lib.rs","--color","never","--crate-type","lib","--emit=dep-info,metadata","-C","debuginfo=2","--cfg","feature=\"hostname\"","--cfg","feature=\"system\"","-C","metadata=5128a49114568ba7","-C","extra-filename=-5128a49114568ba7","--out-dir","/Users/kafuhamada/Documents/Study/Python/Flask/ipu/plugin_market/target/rls/debug/deps","-L","dependency=/Users/kafuhamada/Documents/Study/Python/Flask/ipu/plugin_market/target/rls/debug/deps","--extern","hostname=/Users/kafuhamada/Documents/Study/Python/Flask/ipu/plugin_market/target/rls/debug/deps/libhostname-56f3d7cb97598f9b.rmeta","--extern","quick_error=/Users/kafuhamada/Documents/Study/Python/Flask/ipu/plugin_market/target/rls/debug/deps/libquick_error-4867bdf8f694e2d8.rmeta","--cap-lints","allow","--error-format=json","--sysroot","/Users/kafuhamada/.rustup/toolchains/stable-x86_64-apple-darwin"],"output":[47,85,115,101,114,115,47,107,97,102,117,104,97,109,97,100,97,47,68,111,99,117,109,101,110,116,115,47,83,116,117,100,121,47,80,121,116,104,111,110,47,70,108,97,115,107,47,105,112,117,47,112,108,117,103,105,110,95,109,97,114,107,101,116,47,116,97,114,103,101,116,47,114,108,115,47,100,101,98,117,103,47,100,101,112,115,47,108,105,98,114,101,115,111,108,118,95,99,111,110,102,45,53,49,50,56,97,52,57,49,49,52,53,54,56,98,97,55,46,114,109,101,116,97]},"prelude":{"crate_id":{"name":"resolv_conf","disambiguator":[6344089248551268417,16118001063660755449]},"crate_root":"/Users/kafuhamada/.cargo/registry/src/github.com-1ecc6299db9ec823/resolv-conf-0.6.2/src","external_crates":[{"file_name":"/Users/kafuhamada/.cargo/registry/src/github.com-1ecc6299db9ec823/resolv-conf-0.6.2/src/lib.rs","num":1,"id":{"name":"std","disambiguator":[10276720879801066790,7270037695145965846]}},{"file_name":"/Users/kafuhamada/.cargo/registry/src/github.com-1ecc6299db9ec823/resolv-conf-0.6.2/src/lib.rs","num":2,"id":{"name":"core","disambiguator":[10081619512596250754,7636038010184307036]}},{"file_name":"/Users/kafuhamada/.cargo/registry/src/github.com-1ecc6299db9ec823/resolv-conf-0.6.2/src/lib.rs","num":3,"id":{"name":"compiler_builtins","disambiguator":[530680240650180892,17676251987033652714]}},{"file_name":"/Users/kafuhamada/.cargo/registry/src/github.com-1ecc6299db9ec823/resolv-conf-0.6.2/src/lib.rs","num":4,"id":{"name":"rustc_std_workspace_core","disambiguator":[11705792804325932575,5133282415091935280]}},{"file_name":"/Users/kafuhamada/.cargo/registry/src/github.com-1ecc6299db9ec823/resolv-conf-0.6.2/src/lib.rs","num":5,"id":{"name":"alloc","disambiguator":[17612447423192331107,152287996219017673]}},{"file_name":"/Users/kafuhamada/.cargo/registry/src/github.com-1ecc6299db9ec823/resolv-conf-0.6.2/src/lib.rs","num":6,"id":{"name":"libc","disambiguator":[4726535560424510965,12625991608955964180]}},{"file_name":"/Users/kafuhamada/.cargo/registry/src/github.com-1ecc6299db9ec823/resolv-conf-0.6.2/src/lib.rs","num":7,"id":{"name":"rustc_demangle","disambiguator":[2075391902352510242,6907956565514940343]}},{"file_name":"/Users/kafuhamada/.cargo/registry/src/github.com-1ecc6299db9ec823/resolv-conf-0.6.2/src/lib.rs","num":8,"id":{"name":"unwind","disambiguator":[1151212087006369140,11441208638619140056]}},{"file_name":"/Users/kafuhamada/.cargo/registry/src/github.com-1ecc6299db9ec823/resolv-conf-0.6.2/src/lib.rs","num":9,"id":{"name":"backtrace_sys","disambiguator":[8447635395464762154,8931705543987386293]}},{"file_name":"/Users/kafuhamada/.cargo/registry/src/github.com-1ecc6299db9ec823/resolv-conf-0.6.2/src/lib.rs","num":10,"id":{"name":"panic_unwind","disambiguator":[8817718997728662164,16991859756432700022]}},{"file_name":"/Users/kafuhamada/.cargo/registry/src/github.com-1ecc6299db9ec823/resolv-conf-0.6.2/src/lib.rs","num":11,"id":{"name":"quick_error","disambiguator":[18211776762110451307,15910305138578207112]}},{"file_name":"/Users/kafuhamada/.cargo/registry/src/github.com-1ecc6299db9ec823/resolv-conf-0.6.2/src/lib.rs","num":12,"id":{"name":"hostname","disambiguator":[2004869852370009427,249173684100280148]}},{"file_name":"/Users/kafuhamada/.cargo/registry/src/github.com-1ecc6299db9ec823/resolv-conf-0.6.2/src/lib.rs","num":13,"id":{"name":"libc","disambiguator":[12754417319316353838,2533270702905957675]}}],"span":{"file_name":[47,85,115,101,114,115,47,107,97,102,117,104,97,109,97,100,97,47,46,99,97,114,103,111,47,114,101,103,105,115,116,114,121,47,115,114,99,47,103,105,116,104,117,98,46,99,111,109,45,49,101,99,99,54,50,57,57,100,98,57,101,99,56,50,51,47,114,101,115,111,108,118,45,99,111,110,102,45,48,46,54,46,50,47,115,114,99,47,108,105,98,46,114,115],"byte_start":0,"byte_end":3297,"line_start":1,"line_end":105,"column_start":1,"column_end":54}},"imports":[{"kind":"Use","ref_id":{"krate":0,"index":200},"span":{"file_name":[47,85,115,101,114,115,47,107,97,102,117,104,97,109,97,100,97,47,46,99,97,114,103,111,47,114,101,103,105,115,116,114,121,47,115,114,99,47,103,105,116,104,117,98,46,99,111,109,45,49,101,99,99,54,50,57,57,100,98,57,101,99,56,50,51,47,114,101,115,111,108,118,45,99,111,110,102,45,48,46,54,46,50,47,115,114,99,47,108,105,98,46,114,115],"byte_start":3183,"byte_end":3193,"line_start":103,"line_end":103,"column_start":18,"column_end":28},"alias_span":null,"name":"ParseError","value":"","parent":{"krate":0,"index":0}},{"kind":"Use","ref_id":{"krate":0,"index":256},"span":{"file_name":[47,85,115,101,114,115,47,107,97,102,117,104,97,109,97,100,97,47,46,99,97,114,103,111,47,114,101,103,105,115,116,114,121,47,115,114,99,47,103,105,116,104,117,98,46,99,111,109,45,49,101,99,99,54,50,57,57,100,98,57,101,99,56,50,51,47,114,101,115,111,108,118,45,99,111,110,102,45,48,46,54,46,50,47,115,114,99,47,108,105,98,46,114,115],"byte_start":3208,"byte_end":3222,"line_start":104,"line_end":104,"column_start":14,"column_end":28},"alias_span":null,"name":"AddrParseError","value":"","parent":{"krate":0,"index":0}},{"kind":"Use","ref_id":{"krate":0,"index":216},"span":{"file_name":[47,85,115,101,114,115,47,107,97,102,117,104,97,109,97,100,97,47,46,99,97,114,103,111,47,114,101,103,105,115,116,114,121,47,115,114,99,47,103,105,116,104,117,98,46,99,111,109,45,49,101,99,99,54,50,57,57,100,98,57,101,99,56,50,51,47,114,101,115,111,108,118,45,99,111,110,102,45,48,46,54,46,50,47,115,114,99,47,108,105,98,46,114,115],"byte_start":3224,"byte_end":3231,"line_start":104,"line_end":104,"column_start":30,"column_end":37},"alias_span":null,"name":"Network","value":"","parent":{"krate":0,"index":0}},{"kind":"Use","ref_id":{"krate":0,"index":236},"span":{"file_name":[47,85,115,101,114,115,47,107,97,102,117,104,97,109,97,100,97,47,46,99,97,114,103,111,47,114,101,103,105,115,116,114,121,47,115,114,99,47,103,105,116,104,117,98,46,99,111,109,45,49,101,99,99,54,50,57,57,100,98,57,101,99,56,50,51,47,114,101,115,111,108,118,45,99,111,110,102,45,48,46,54,46,50,47,115,114,99,47,108,105,98,46,114,115],"byte_start":3233,"byte_end":3241,"line_start":104,"line_end":104,"column_start":39,"column_end":47},"alias_span":null,"name":"ScopedIp","value":"","parent":{"krate":0,"index":0}},{"kind":"Use","ref_id":{"krate":0,"index":294},"span":{"file_name":[47,85,115,101,114,115,47,107,97,102,117,104,97,109,97,100,97,47,46,99,97,114,103,111,47,114,101,103,105,115,116,114,121,47,115,114,99,47,103,105,116,104,117,98,46,99,111,109,45,49,101,99,99,54,50,57,57,100,98,57,101,99,56,50,51,47,114,101,115,111,108,118,45,99,111,110,102,45,48,46,54,46,50,47,115,114,99,47,108,105,98,46,114,115],"byte_start":3261,"byte_end":3267,"line_start":105,"line_end":105,"column_start":18,"column_end":24},"alias_span":null,"name":"Config","value":"","parent":{"krate":0,"index":0}},{"kind":"Use","ref_id":{"krate":0,"index":314},"span":{"file_name":[47,85,115,101,114,115,47,107,97,102,117,104,97,109,97,100,97,47,46,99,97,114,103,111,47,114,101,103,105,115,116,114,121,47,115,114,99,47,103,105,116,104,117,98,46,99,111,109,45,49,101,99,99,54,50,57,57,100,98,57,101,99,56,50,51,47,114,101,115,111,108,118,45,99,111,110,102,45,48,46,54,46,50,47,115,114,99,47,108,105,98,46,114,115],"byte_start":3269,"byte_end":3279,"line_start":105,"line_end":105,"column_start":26,"column_end":36},"alias_span":null,"name":"DomainIter","value":"","parent":{"krate":0,"index":0}},{"kind":"Use","ref_id":{"krate":0,"index":334},"span":{"file_name":[47,85,115,101,114,115,47,107,97,102,117,104,97,109,97,100,97,47,46,99,97,114,103,111,47,114,101,103,105,115,116,114,121,47,115,114,99,47,103,105,116,104,117,98,46,99,111,109,45,49,101,99,99,54,50,57,57,100,98,57,101,99,56,50,51,47,114,101,115,111,108,118,45,99,111,110,102,45,48,46,54,46,50,47,115,114,99,47,108,105,98,46,114,115],"byte_start":3281,"byte_end":3287,"line_start":105,"line_end":105,"column_start":38,"column_end":44},"alias_span":null,"name":"Lookup","value":"","parent":{"krate":0,"index":0}},{"kind":"Use","ref_id":{"krate":0,"index":354},"span":{"file_name":[47,85,115,101,114,115,47,107,97,102,117,104,97,109,97,100,97,47,46,99,97,114,103,111,47,114,101,103,105,115,116,114,121,47,115,114,99,47,103,105,116,104,117,98,46,99,111,109,45,49,101,99,99,54,50,57,57,100,98,57,101,99,56,50,51,47,114,101,115,111,108,118,45,99,111,110,102,45,48,46,54,46,50,47,115,114,99,47,108,105,98,46,114,115],"byte_start":3289,"byte_end":3295,"line_start":105,"line_end":105,"column_start":46,"column_end":52},"alias_span":null,"name":"Family","value":"","parent":{"krate":0,"index":0}}],"defs":[{"kind":"Mod","id":{"krate":0,"index":0},"span":{"file_name":[47,85,115,101,114,115,47,107,97,102,117,104,97,109,97,100,97,47,46,99,97,114,103,111,47,114,101,103,105,115,116,114,121,47,115,114,99,47,103,105,116,104,117,98,46,99,111,109,45,49,101,99,99,54,50,57,57,100,98,57,101,99,56,50,51,47,114,101,115,111,108,118,45,99,111,110,102,45,48,46,54,46,50,47,115,114,99,47,108,105,98,46,114,115],"byte_start":0,"byte_end":3297,"line_start":1,"line_end":105,"column_start":1,"column_end":54},"name":"","qualname":"::","value":"/Users/kafuhamada/.cargo/registry/src/github.com-1ecc6299db9ec823/resolv-conf-0.6.2/src/lib.rs","parent":null,"children":[{"krate":0,"index":2},{"krate":0,"index":4},{"krate":0,"index":6},{"krate":0,"index":8},{"krate":0,"index":10},{"krate":0,"index":44},{"krate":0,"index":106},{"krate":0,"index":180},{"krate":0,"index":182},{"krate":0,"index":190}],"decl_id":null,"docs":" The crate simply parses `/etc/resolv.conf` file and creates a config object","sig":null,"attributes":[{"value":"warn(missing_debug_implementations)","span":{"file_name":[47,85,115,101,114,115,47,107,97,102,117,104,97,109,97,100,97,47,46,99,97,114,103,111,47,114,101,103,105,115,116,114,121,47,115,114,99,47,103,105,116,104,117,98,46,99,111,109,45,49,101,99,99,54,50,57,57,100,98,57,101,99,56,50,51,47,114,101,115,111,108,118,45,99,111,110,102,45,48,46,54,46,50,47,115,114,99,47,108,105,98,46,114,115],"byte_start":2978,"byte_end":3017,"line_start":91,"line_end":91,"column_start":1,"column_end":40}},{"value":"warn(missing_docs)","span":{"file_name":[47,85,115,101,114,115,47,107,97,102,117,104,97,109,97,100,97,47,46,99,97,114,103,111,47,114,101,103,105,115,116,114,121,47,115,114,99,47,103,105,116,104,117,98,46,99,111,109,45,49,101,99,99,54,50,57,57,100,98,57,101,99,56,50,51,47,114,101,115,111,108,118,45,99,111,110,102,45,48,46,54,46,50,47,115,114,99,47,108,105,98,46,114,115],"byte_start":3018,"byte_end":3040,"line_start":92,"line_end":92,"column_start":1,"column_end":23}}]},{"kind":"TupleVariant","id":{"krate":0,"index":67},"span":{"file_name":[47,85,115,101,114,115,47,107,97,102,117,104,97,109,97,100,97,47,46,99,97,114,103,111,47,114,101,103,105,115,116,114,121,47,115,114,99,47,103,105,116,104,117,98,46,99,111,109,45,49,101,99,99,54,50,57,57,100,98,57,101,99,56,50,51,47,114,101,115,111,108,118,45,99,111,110,102,45,48,46,54,46,50,47,115,114,99,47,103,114,97,109,109,97,114,46,114,115],"byte_start":3641,"byte_end":3652,"line_start":11,"line_end":11,"column_start":9,"column_end":20},"name":"InvalidUtf8","qualname":"::grammar::ParseError::InvalidUtf8","value":"ParseError::InvalidUtf8(usize, Utf8Error)","parent":{"krate":0,"index":200},"children":[],"decl_id":null,"docs":" Error that may be returned when the string to parse contains invalid UTF-8 sequences\n","sig":null,"attributes":[]},{"kind":"TupleVariant","id":{"krate":0,"index":73},"span":{"file_name":[47,85,115,101,114,115,47,107,97,102,117,104,97,109,97,100,97,47,46,99,97,114,103,111,47,114,101,103,105,115,116,114,121,47,115,114,99,47,103,105,116,104,117,98,46,99,111,109,45,49,101,99,99,54,50,57,57,100,98,57,101,99,56,50,51,47,114,101,115,111,108,118,45,99,111,110,102,45,48,46,54,46,50,47,115,114,99,47,103,114,97,109,109,97,114,46,114,115],"byte_start":3950,"byte_end":3962,"line_start":17,"line_end":17,"column_start":9,"column_end":21},"name":"InvalidValue","qualname":"::grammar::ParseError::InvalidValue","value":"ParseError::InvalidValue(usize)","parent":{"krate":0,"index":200},"children":[],"decl_id":null,"docs":" Error returned a value for a given directive is invalid.\n This can also happen when the value is missing, if the directive requires a value.\n","sig":null,"attributes":[]},{"kind":"TupleVariant","id":{"krate":0,"index":77},"span":{"file_name":[47,85,115,101,114,115,47,107,97,102,117,104,97,109,97,100,97,47,46,99,97,114,103,111,47,114,101,103,105,115,116,114,121,47,115,114,99,47,103,105,116,104,117,98,46,99,111,109,45,49,101,99,99,54,50,57,57,100,98,57,101,99,56,50,51,47,114,101,115,111,108,118,45,99,111,110,102,45,48,46,54,46,50,47,115,114,99,47,103,114,97,109,109,97,114,46,114,115],"byte_start":4277,"byte_end":4295,"line_start":23,"line_end":23,"column_start":9,"column_end":27},"name":"InvalidOptionValue","qualname":"::grammar::ParseError::InvalidOptionValue","value":"ParseError::InvalidOptionValue(usize)","parent":{"krate":0,"index":200},"children":[],"decl_id":null,"docs":" Error returned when a value for a given option is invalid.\n This can also happen when the value is missing, if the option requires a value.\n","sig":null,"attributes":[]},{"kind":"TupleVariant","id":{"krate":0,"index":81},"span":{"file_name":[47,85,115,101,114,115,47,107,97,102,117,104,97,109,97,100,97,47,46,99,97,114,103,111,47,114,101,103,105,115,116,114,121,47,115,114,99,47,103,105,116,104,117,98,46,99,111,109,45,49,101,99,99,54,50,57,57,100,98,57,101,99,56,50,51,47,114,101,115,111,108,118,45,99,111,110,102,45,48,46,54,46,50,47,115,114,99,47,103,114,97,109,109,97,114,46,114,115],"byte_start":4502,"byte_end":4515,"line_start":28,"line_end":28,"column_start":9,"column_end":22},"name":"InvalidOption","qualname":"::grammar::ParseError::InvalidOption","value":"ParseError::InvalidOption(usize)","parent":{"krate":0,"index":200},"children":[],"decl_id":null,"docs":" Error returned when a invalid option is found.\n","sig":null,"attributes":[]},{"kind":"TupleVariant","id":{"krate":0,"index":85},"span":{"file_name":[47,85,115,101,114,115,47,107,97,102,117,104,97,109,97,100,97,47,46,99,97,114,103,111,47,114,101,103,105,115,116,114,121,47,115,114,99,47,103,105,116,104,117,98,46,99,111,109,45,49,101,99,99,54,50,57,57,100,98,57,101,99,56,50,51,47,114,101,115,111,108,118,45,99,111,110,102,45,48,46,54,46,50,47,115,114,99,47,103,114,97,109,109,97,114,46,114,115],"byte_start":4676,"byte_end":4692,"line_start":32,"line_end":32,"column_start":9,"column_end":25},"name":"InvalidDirective","qualname":"::grammar::ParseError::InvalidDirective","value":"ParseError::InvalidDirective(usize)","parent":{"krate":0,"index":200},"children":[],"decl_id":null,"docs":" Error returned when a invalid directive is found.\n","sig":null,"attributes":[]},{"kind":"TupleVariant","id":{"krate":0,"index":89},"span":{"file_name":[47,85,115,101,114,115,47,107,97,102,117,104,97,109,97,100,97,47,46,99,97,114,103,111,47,114,101,103,105,115,116,114,121,47,115,114,99,47,103,105,116,104,117,98,46,99,111,109,45,49,101,99,99,54,50,57,57,100,98,57,101,99,56,50,51,47,114,101,115,111,108,118,45,99,111,110,102,45,48,46,54,46,50,47,115,114,99,47,103,114,97,109,109,97,114,46,114,115],"byte_start":4869,"byte_end":4878,"line_start":36,"line_end":36,"column_start":9,"column_end":18},"name":"InvalidIp","qualname":"::grammar::ParseError::InvalidIp","value":"ParseError::InvalidIp(usize, AddrParseError)","parent":{"krate":0,"index":200},"children":[],"decl_id":null,"docs":" Error returned when a value cannot be parsed an an IP address.\n","sig":null,"attributes":[]},{"kind":"TupleVariant","id":{"krate":0,"index":95},"span":{"file_name":[47,85,115,101,114,115,47,107,97,102,117,104,97,109,97,100,97,47,46,99,97,114,103,111,47,114,101,103,105,115,116,114,121,47,115,114,99,47,103,105,116,104,117,98,46,99,111,109,45,49,101,99,99,54,50,57,57,100,98,57,101,99,56,50,51,47,114,101,115,111,108,118,45,99,111,110,102,45,48,46,54,46,50,47,115,114,99,47,103,114,97,109,109,97,114,46,114,115],"byte_start":5086,"byte_end":5095,"line_start":40,"line_end":40,"column_start":9,"column_end":18},"name":"ExtraData","qualname":"::grammar::ParseError::ExtraData","value":"ParseError::ExtraData(usize)","parent":{"krate":0,"index":200},"children":[],"decl_id":null,"docs":" Error returned when there is extra data at the end of a line.\n","sig":null,"attributes":[]},{"kind":"Enum","id":{"krate":0,"index":200},"span":{"file_name":[47,85,115,101,114,115,47,107,97,102,117,104,97,109,97,100,97,47,46,99,97,114,103,111,47,114,101,103,105,115,116,114,121,47,115,114,99,47,103,105,116,104,117,98,46,99,111,109,45,49,101,99,99,54,50,57,57,100,98,57,101,99,56,50,51,47,114,101,115,111,108,118,45,99,111,110,102,45,48,46,54,46,50,47,115,114,99,47,103,114,97,109,109,97,114,46,114,115],"byte_start":3523,"byte_end":3533,"line_start":9,"line_end":9,"column_start":14,"column_end":24},"name":"ParseError","qualname":"::grammar::ParseError","value":"ParseError::{InvalidUtf8, InvalidValue, InvalidOptionValue, InvalidOption, InvalidDirective, InvalidIp, ExtraData}","parent":null,"children":[{"krate":0,"index":67},{"krate":0,"index":73},{"krate":0,"index":77},{"krate":0,"index":81},{"krate":0,"index":85},{"krate":0,"index":89},{"krate":0,"index":95}],"decl_id":null,"docs":" Error while parsing resolv.conf file\n","sig":null,"attributes":[{"value":"allow(unknown_lints)","span":{"file_name":[60,58,58,113,117,105,99,107,95,101,114,114,111,114,58,58,113,117,105,99,107,95,101,114,114,111,114,32,109,97,99,114,111,115,62],"byte_start":8228720,"byte_end":8228749,"line_start":199,"line_end":199,"column_start":1,"column_end":30}},{"value":"allow(renamed_and_removed_lints)","span":{"file_name":[60,58,58,113,117,105,99,107,95,101,114,114,111,114,58,58,113,117,105,99,107,95,101,114,114,111,114,32,109,97,99,114,111,115,62],"byte_start":8228750,"byte_end":8228791,"line_start":199,"line_end":199,"column_start":31,"column_end":72}},{"value":"allow(unused_doc_comment)","span":{"file_name":[60,58,58,113,117,105,99,107,95,101,114,114,111,114,58,58,113,117,105,99,107,95,101,114,114,111,114,32,109,97,99,114,111,115,62],"byte_start":8228792,"byte_end":8228826,"line_start":199,"line_end":200,"column_start":73,"column_end":31}},{"value":"allow(unused_doc_comments)","span":{"file_name":[60,58,58,113,117,105,99,107,95,101,114,114,111,114,58,58,113,117,105,99,107,95,101,114,114,111,114,32,109,97,99,114,111,115,62],"byte_start":8228827,"byte_end":8228862,"line_start":200,"line_end":200,"column_start":32,"column_end":67}}]},{"kind":"TupleVariant","id":{"krate":0,"index":113},"span":{"file_name":[47,85,115,101,114,115,47,107,97,102,117,104,97,109,97,100,97,47,46,99,97,114,103,111,47,114,101,103,105,115,116,114,121,47,115,114,99,47,103,105,116,104,117,98,46,99,111,109,45,49,101,99,99,54,50,57,57,100,98,57,101,99,56,50,51,47,114,101,115,111,108,118,45,99,111,110,102,45,48,46,54,46,50,47,115,114,99,47,105,112,46,114,115],"byte_start":12534,"byte_end":12536,"line_start":10,"line_end":10,"column_start":5,"column_end":7},"name":"V4","qualname":"::ip::Network::V4","value":"Network::V4(Ipv4Addr, Ipv4Addr)","parent":{"krate":0,"index":216},"children":[],"decl_id":null,"docs":" Represent an IPv4 network address\n","sig":null,"attributes":[]},{"kind":"TupleVariant","id":{"krate":0,"index":119},"span":{"file_name":[47,85,115,101,114,115,47,107,97,102,117,104,97,109,97,100,97,47,46,99,97,114,103,111,47,114,101,103,105,115,116,114,121,47,115,114,99,47,103,105,116,104,117,98,46,99,111,109,45,49,101,99,99,54,50,57,57,100,98,57,101,99,56,50,51,47,114,101,115,111,108,118,45,99,111,110,102,45,48,46,54,46,50,47,115,114,99,47,105,112,46,114,115],"byte_start":12604,"byte_end":12606,"line_start":12,"line_end":12,"column_start":5,"column_end":7},"name":"V6","qualname":"::ip::Network::V6","value":"Network::V6(Ipv6Addr, Ipv6Addr)","parent":{"krate":0,"index":216},"children":[],"decl_id":null,"docs":" Represent an IPv6 network address\n","sig":null,"attributes":[]},{"kind":"Enum","id":{"krate":0,"index":216},"span":{"file_name":[47,85,115,101,114,115,47,107,97,102,117,104,97,109,97,100,97,47,46,99,97,114,103,111,47,114,101,103,105,115,116,114,121,47,115,114,99,47,103,105,116,104,117,98,46,99,111,109,45,49,101,99,99,54,50,57,57,100,98,57,101,99,56,50,51,47,114,101,115,111,108,118,45,99,111,110,102,45,48,46,54,46,50,47,115,114,99,47,105,112,46,114,115],"byte_start":12478,"byte_end":12485,"line_start":8,"line_end":8,"column_start":10,"column_end":17},"name":"Network","qualname":"::ip::Network","value":"Network::{V4, V6}","parent":null,"children":[{"krate":0,"index":113},{"krate":0,"index":119}],"decl_id":null,"docs":" A network, that is an IP address and a mask\n","sig":null,"attributes":[{"value":"structural_match","span":{"file_name":[47,85,115,101,114,115,47,107,97,102,117,104,97,109,97,100,97,47,46,99,97,114,103,111,47,114,101,103,105,115,116,114,121,47,115,114,99,47,103,105,116,104,117,98,46,99,111,109,45,49,101,99,99,54,50,57,57,100,98,57,101,99,56,50,51,47,114,101,115,111,108,118,45,99,111,110,102,45,48,46,54,46,50,47,115,114,99,47,105,112,46,114,115],"byte_start":12469,"byte_end":12629,"line_start":8,"line_end":13,"column_start":1,"column_end":2}}]},{"kind":"TupleVariant","id":{"krate":0,"index":125},"span":{"file_name":[47,85,115,101,114,115,47,107,97,102,117,104,97,109,97,100,97,47,46,99,97,114,103,111,47,114,101,103,105,115,116,114,121,47,115,114,99,47,103,105,116,104,117,98,46,99,111,109,45,49,101,99,99,54,50,57,57,100,98,57,101,99,56,50,51,47,114,101,115,111,108,118,45,99,111,110,102,45,48,46,54,46,50,47,115,114,99,47,105,112,46,114,115],"byte_start":13136,"byte_end":13138,"line_start":29,"line_end":29,"column_start":5,"column_end":7},"name":"V4","qualname":"::ip::ScopedIp::V4","value":"ScopedIp::V4(Ipv4Addr)","parent":{"krate":0,"index":236},"children":[],"decl_id":null,"docs":" Represent an IPv4 address\n","sig":null,"attributes":[]},{"kind":"TupleVariant","id":{"krate":0,"index":129},"span":{"file_name":[47,85,115,101,114,115,47,107,97,102,117,104,97,109,97,100,97,47,46,99,97,114,103,111,47,114,101,103,105,115,116,114,121,47,115,114,99,47,103,105,116,104,117,98,46,99,111,109,45,49,101,99,99,54,50,57,57,100,98,57,101,99,56,50,51,47,114,101,115,111,108,118,45,99,111,110,102,45,48,46,54,46,50,47,115,114,99,47,105,112,46,114,115],"byte_start":13213,"byte_end":13215,"line_start":31,"line_end":31,"column_start":5,"column_end":7},"name":"V6","qualname":"::ip::ScopedIp::V6","value":"ScopedIp::V6(Ipv6Addr, Option<String>)","parent":{"krate":0,"index":236},"children":[],"decl_id":null,"docs":" Represent an IPv6 and its scope identifier, if any\n","sig":null,"attributes":[]},{"kind":"Enum","id":{"krate":0,"index":236},"span":{"file_name":[47,85,115,101,114,115,47,107,97,102,117,104,97,109,97,100,97,47,46,99,97,114,103,111,47,114,101,103,105,115,116,114,121,47,115,114,99,47,103,105,116,104,117,98,46,99,111,109,45,49,101,99,99,54,50,57,57,100,98,57,101,99,56,50,51,47,114,101,115,111,108,118,45,99,111,110,102,45,48,46,54,46,50,47,115,114,99,47,105,112,46,114,115],"byte_start":13087,"byte_end":13095,"line_start":27,"line_end":27,"column_start":10,"column_end":18},"name":"ScopedIp","qualname":"::ip::ScopedIp","value":"ScopedIp::{V4, V6}","parent":null,"children":[{"krate":0,"index":125},{"krate":0,"index":129}],"decl_id":null,"docs":" Represent an IP address. This type is similar to `std::net::IpAddr` but it supports IPv6 scope\n identifiers.\n","sig":null,"attributes":[{"value":"structural_match","span":{"file_name":[47,85,115,101,114,115,47,107,97,102,117,104,97,109,97,100,97,47,46,99,97,114,103,111,47,114,101,103,105,115,116,114,121,47,115,114,99,47,103,105,116,104,117,98,46,99,111,109,45,49,101,99,99,54,50,57,57,100,98,57,101,99,56,50,51,47,114,101,115,111,108,118,45,99,111,110,102,45,48,46,54,46,50,47,115,114,99,47,105,112,46,114,115],"byte_start":13078,"byte_end":13244,"line_start":27,"line_end":32,"column_start":1,"column_end":2}}]},{"kind":"Struct","id":{"krate":0,"index":256},"span":{"file_name":[47,85,115,101,114,115,47,107,97,102,117,104,97,109,97,100,97,47,46,99,97,114,103,111,47,114,101,103,105,115,116,114,121,47,115,114,99,47,103,105,116,104,117,98,46,99,111,109,45,49,101,99,99,54,50,57,57,100,98,57,101,99,56,50,51,47,114,101,115,111,108,118,45,99,111,110,102,45,48,46,54,46,50,47,115,114,99,47,105,112,46,114,115],"byte_start":15732,"byte_end":15746,"line_start":118,"line_end":118,"column_start":12,"column_end":26},"name":"AddrParseError","qualname":"::ip::AddrParseError","value":"","parent":null,"children":[],"decl_id":null,"docs":" An error which can be returned when parsing an IP address.\n","sig":null,"attributes":[{"value":"structural_match","span":{"file_name":[47,85,115,101,114,115,47,107,97,102,117,104,97,109,97,100,97,47,46,99,97,114,103,111,47,114,101,103,105,115,116,114,121,47,115,114,99,47,103,105,116,104,117,98,46,99,111,109,45,49,101,99,99,54,50,57,57,100,98,57,101,99,56,50,51,47,114,101,115,111,108,118,45,99,111,110,102,45,48,46,54,46,50,47,115,114,99,47,105,112,46,114,115],"byte_start":15721,"byte_end":15747,"line_start":118,"line_end":118,"column_start":1,"column_end":27}}]},{"kind":"Struct","id":{"krate":0,"index":294},"span":{"file_name":[47,85,115,101,114,115,47,107,97,102,117,104,97,109,97,100,97,47,46,99,97,114,103,111,47,114,101,103,105,115,116,114,121,47,115,114,99,47,103,105,116,104,117,98,46,99,111,109,45,49,101,99,99,54,50,57,57,100,98,57,101,99,56,50,51,47,114,101,115,111,108,118,45,99,111,110,102,45,48,46,54,46,50,47,115,114,99,47,99,111,110,102,105,103,46,114,115],"byte_start":17953,"byte_end":17959,"line_start":56,"line_end":56,"column_start":12,"column_end":18},"name":"Config","qualname":"::config::Config","value":"Config { nameservers, sortlist, debug, ndots, timeout, attempts, rotate, no_check_names, inet6, ip6_bytestring, ip6_dotint, edns0, single_request, single_request_reopen, no_tld_query, use_vc, lookup, family }","parent":null,"children":[{"krate":0,"index":143},{"krate":0,"index":145},{"krate":0,"index":147},{"krate":0,"index":149},{"krate":0,"index":151},{"krate":0,"index":153},{"krate":0,"index":155},{"krate":0,"index":157},{"krate":0,"index":159},{"krate":0,"index":161},{"krate":0,"index":163},{"krate":0,"index":165},{"krate":0,"index":167},{"krate":0,"index":169},{"krate":0,"index":171},{"krate":0,"index":173},{"krate":0,"index":175},{"krate":0,"index":177},{"krate":0,"index":179},{"krate":0,"index":181},{"krate":0,"index":183}],"decl_id":null,"docs":" Represent a resolver configuration, as described in `man 5 resolv.conf`.\n The options and defaults match those in the linux `man` page.","sig":null,"attributes":[{"value":"structural_match","span":{"file_name":[47,85,115,101,114,115,47,107,97,102,117,104,97,109,97,100,97,47,46,99,97,114,103,111,47,114,101,103,105,115,116,114,121,47,115,114,99,47,103,105,116,104,117,98,46,99,111,109,45,49,101,99,99,54,50,57,57,100,98,57,101,99,56,50,51,47,114,101,115,111,108,118,45,99,111,110,102,45,48,46,54,46,50,47,115,114,99,47,99,111,110,102,105,103,46,114,115],"byte_start":17942,"byte_end":20085,"line_start":56,"line_end":106,"column_start":1,"column_end":2}}]},{"kind":"Field","id":{"krate":0,"index":143},"span":{"file_name":[47,85,115,101,114,115,47,107,97,102,117,104,97,109,97,100,97,47,46,99,97,114,103,111,47,114,101,103,105,115,116,114,121,47,115,114,99,47,103,105,116,104,117,98,46,99,111,109,45,49,101,99,99,54,50,57,57,100,98,57,101,99,56,50,51,47,114,101,115,111,108,118,45,99,111,110,102,45,48,46,54,46,50,47,115,114,99,47,99,111,110,102,105,103,46,114,115],"byte_start":17998,"byte_end":18009,"line_start":58,"line_end":58,"column_start":9,"column_end":20},"name":"nameservers","qualname":"::config::Config::nameservers","value":"std::vec::Vec<ip::ScopedIp>","parent":{"krate":0,"index":294},"children":[],"decl_id":null,"docs":" List of nameservers\n","sig":null,"attributes":[]},{"kind":"Field","id":{"krate":0,"index":151},"span":{"file_name":[47,85,115,101,114,115,47,107,97,102,117,104,97,109,97,100,97,47,46,99,97,114,103,111,47,114,101,103,105,115,116,114,121,47,115,114,99,47,103,105,116,104,117,98,46,99,111,109,45,49,101,99,99,54,50,57,57,100,98,57,101,99,56,50,51,47,114,101,115,111,108,118,45,99,111,110,102,45,48,46,54,46,50,47,115,114,99,47,99,111,110,102,105,103,46,114,115],"byte_start":18614,"byte_end":18622,"line_start":69,"line_end":69,"column_start":9,"column_end":17},"name":"sortlist","qualname":"::config::Config::sortlist","value":"std::vec::Vec<ip::Network>","parent":{"krate":0,"index":294},"children":[],"decl_id":null,"docs":" List of preferred addresses\n","sig":null,"attributes":[]},{"kind":"Field","id":{"krate":0,"index":153},"span":{"file_name":[47,85,115,101,114,115,47,107,97,102,117,104,97,109,97,100,97,47,46,99,97,114,103,111,47,114,101,103,105,115,116,114,121,47,115,114,99,47,103,105,116,104,117,98,46,99,111,109,45,49,101,99,99,54,50,57,57,100,98,57,101,99,56,50,51,47,114,101,115,111,108,118,45,99,111,110,102,45,48,46,54,46,50,47,115,114,99,47,99,111,110,102,105,103,46,114,115],"byte_start":18683,"byte_end":18688,"line_start":71,"line_end":71,"column_start":9,"column_end":14},"name":"debug","qualname":"::config::Config::debug","value":"bool","parent":{"krate":0,"index":294},"children":[],"decl_id":null,"docs":" Enable DNS resolve debugging\n","sig":null,"attributes":[]},{"kind":"Field","id":{"krate":0,"index":155},"span":{"file_name":[47,85,115,101,114,115,47,107,97,102,117,104,97,109,97,100,97,47,46,99,97,114,103,111,47,114,101,103,105,115,116,114,121,47,115,114,99,47,103,105,116,104,117,98,46,99,111,109,45,49,101,99,99,54,50,57,57,100,98,57,101,99,56,50,51,47,114,101,115,111,108,118,45,99,111,110,102,45,48,46,54,46,50,47,115,114,99,47,99,111,110,102,105,103,46,114,115],"byte_start":18779,"byte_end":18784,"line_start":73,"line_end":73,"column_start":9,"column_end":14},"name":"ndots","qualname":"::config::Config::ndots","value":"u32","parent":{"krate":0,"index":294},"children":[],"decl_id":null,"docs":" Number of dots in name to try absolute resolving first (default 1)\n","sig":null,"attributes":[]},{"kind":"Field","id":{"krate":0,"index":157},"span":{"file_name":[47,85,115,101,114,115,47,107,97,102,117,104,97,109,97,100,97,47,46,99,97,114,103,111,47,114,101,103,105,115,116,114,121,47,115,114,99,47,103,105,116,104,117,98,46,99,111,109,45,49,101,99,99,54,50,57,57,100,98,57,101,99,56,50,51,47,114,101,115,111,108,118,45,99,111,110,102,45,48,46,54,46,50,47,115,114,99,47,99,111,110,102,105,103,46,114,115],"byte_start":18843,"byte_end":18850,"line_start":75,"line_end":75,"column_start":9,"column_end":16},"name":"timeout","qualname":"::config::Config::timeout","value":"u32","parent":{"krate":0,"index":294},"children":[],"decl_id":null,"docs":" Dns query timeout (default 5 [sec])\n","sig":null,"attributes":[]},{"kind":"Field","id":{"krate":0,"index":159},"span":{"file_name":[47,85,115,101,114,115,47,107,97,102,117,104,97,109,97,100,97,47,46,99,97,114,103,111,47,114,101,103,105,115,116,114,121,47,115,114,99,47,103,105,116,104,117,98,46,99,111,109,45,49,101,99,99,54,50,57,57,100,98,57,101,99,56,50,51,47,114,101,115,111,108,118,45,99,111,110,102,45,48,46,54,46,50,47,115,114,99,47,99,111,110,102,105,103,46,114,115],"byte_start":18945,"byte_end":18953,"line_start":77,"line_end":77,"column_start":9,"column_end":17},"name":"attempts","qualname":"::config::Config::attempts","value":"u32","parent":{"krate":0,"index":294},"children":[],"decl_id":null,"docs":" Number of attempts to resolve name if server is inaccesible (default 2)\n","sig":null,"attributes":[]},{"kind":"Field","id":{"krate":0,"index":161},"span":{"file_name":[47,85,115,101,114,115,47,107,97,102,117,104,97,109,97,100,97,47,46,99,97,114,103,111,47,114,101,103,105,115,116,114,121,47,115,114,99,47,103,105,116,104,117,98,46,99,111,109,45,49,101,99,99,54,50,57,57,100,98,57,101,99,56,50,51,47,114,101,115,111,108,118,45,99,111,110,102,45,48,46,54,46,50,47,115,114,99,47,99,111,110,102,105,103,46,114,115],"byte_start":19025,"byte_end":19031,"line_start":79,"line_end":79,"column_start":9,"column_end":15},"name":"rotate","qualname":"::config::Config::rotate","value":"bool","parent":{"krate":0,"index":294},"children":[],"decl_id":null,"docs":" Round-robin selection of servers (default false)\n","sig":null,"attributes":[]},{"kind":"Field","id":{"krate":0,"index":163},"span":{"file_name":[47,85,115,101,114,115,47,107,97,102,117,104,97,109,97,100,97,47,46,99,97,114,103,111,47,114,101,103,105,115,116,114,121,47,115,114,99,47,103,105,116,104,117,98,46,99,111,109,45,49,101,99,99,54,50,57,57,100,98,57,101,99,56,50,51,47,114,101,115,111,108,118,45,99,111,110,102,45,48,46,54,46,50,47,115,114,99,47,99,111,110,102,105,103,46,114,115],"byte_start":19102,"byte_end":19116,"line_start":81,"line_end":81,"column_start":9,"column_end":23},"name":"no_check_names","qualname":"::config::Config::no_check_names","value":"bool","parent":{"krate":0,"index":294},"children":[],"decl_id":null,"docs":" Don't check names for validity (default false)\n","sig":null,"attributes":[]},{"kind":"Field","id":{"krate":0,"index":165},"span":{"file_name":[47,85,115,101,114,115,47,107,97,102,117,104,97,109,97,100,97,47,46,99,97,114,103,111,47,114,101,103,105,115,116,114,121,47,115,114,99,47,103,105,116,104,117,98,46,99,111,109,45,49,101,99,99,54,50,57,57,100,98,57,101,99,56,50,51,47,114,101,115,111,108,118,45,99,111,110,102,45,48,46,54,46,50,47,115,114,99,47,99,111,110,102,105,103,46,114,115],"byte_start":19164,"byte_end":19169,"line_start":83,"line_end":83,"column_start":9,"column_end":14},"name":"inet6","qualname":"::config::Config::inet6","value":"bool","parent":{"krate":0,"index":294},"children":[],"decl_id":null,"docs":" Try AAAA query before A\n","sig":null,"attributes":[]},{"kind":"Field","id":{"krate":0,"index":167},"span":{"file_name":[47,85,115,101,114,115,47,107,97,102,117,104,97,109,97,100,97,47,46,99,97,114,103,111,47,114,101,103,105,115,116,114,121,47,115,114,99,47,103,105,116,104,117,98,46,99,111,109,45,49,101,99,99,54,50,57,57,100,98,57,101,99,56,50,51,47,114,101,115,111,108,118,45,99,111,110,102,45,48,46,54,46,50,47,115,114,99,47,99,111,110,102,105,103,46,114,115],"byte_start":19286,"byte_end":19300,"line_start":86,"line_end":86,"column_start":9,"column_end":23},"name":"ip6_bytestring","qualname":"::config::Config::ip6_bytestring","value":"bool","parent":{"krate":0,"index":294},"children":[],"decl_id":null,"docs":" Use reverse lookup of ipv6 using bit-label format described instead\n of nibble format\n","sig":null,"attributes":[]},{"kind":"Field","id":{"krate":0,"index":169},"span":{"file_name":[47,85,115,101,114,115,47,107,97,102,117,104,97,109,97,100,97,47,46,99,97,114,103,111,47,114,101,103,105,115,116,114,121,47,115,114,99,47,103,105,116,104,117,98,46,99,111,109,45,49,101,99,99,54,50,57,57,100,98,57,101,99,56,50,51,47,114,101,115,111,108,118,45,99,111,110,102,45,48,46,54,46,50,47,115,114,99,47,99,111,110,102,105,103,46,114,115],"byte_start":19408,"byte_end":19418,"line_start":89,"line_end":89,"column_start":9,"column_end":19},"name":"ip6_dotint","qualname":"::config::Config::ip6_dotint","value":"bool","parent":{"krate":0,"index":294},"children":[],"decl_id":null,"docs":" Do ipv6 reverse lookups in ip6.int zone instead of ip6.arpa\n (default false)\n","sig":null,"attributes":[]},{"kind":"Field","id":{"krate":0,"index":171},"span":{"file_name":[47,85,115,101,114,115,47,107,97,102,117,104,97,109,97,100,97,47,46,99,97,114,103,111,47,114,101,103,105,115,116,114,121,47,115,114,99,47,103,105,116,104,117,98,46,99,111,109,45,49,101,99,99,54,50,57,57,100,98,57,101,99,56,50,51,47,114,101,115,111,108,118,45,99,111,110,102,45,48,46,54,46,50,47,115,114,99,47,99,111,110,102,105,103,46,114,115],"byte_start":19486,"byte_end":19491,"line_start":91,"line_end":91,"column_start":9,"column_end":14},"name":"edns0","qualname":"::config::Config::edns0","value":"bool","parent":{"krate":0,"index":294},"children":[],"decl_id":null,"docs":" Enable dns extensions described in RFC 2671\n","sig":null,"attributes":[]},{"kind":"Field","id":{"krate":0,"index":173},"span":{"file_name":[47,85,115,101,114,115,47,107,97,102,117,104,97,109,97,100,97,47,46,99,97,114,103,111,47,114,101,103,105,115,116,114,121,47,115,114,99,47,103,105,116,104,117,98,46,99,111,109,45,49,101,99,99,54,50,57,57,100,98,57,101,99,56,50,51,47,114,101,115,111,108,118,45,99,111,110,102,45,48,46,54,46,50,47,115,114,99,47,99,111,110,102,105,103,46,114,115],"byte_start":19564,"byte_end":19578,"line_start":93,"line_end":93,"column_start":9,"column_end":23},"name":"single_request","qualname":"::config::Config::single_request","value":"bool","parent":{"krate":0,"index":294},"children":[],"decl_id":null,"docs":" Don't make ipv4 and ipv6 requests simultaneously\n","sig":null,"attributes":[]},{"kind":"Field","id":{"krate":0,"index":175},"span":{"file_name":[47,85,115,101,114,115,47,107,97,102,117,104,97,109,97,100,97,47,46,99,97,114,103,111,47,114,101,103,105,115,116,114,121,47,115,114,99,47,103,105,116,104,117,98,46,99,111,109,45,49,101,99,99,54,50,57,57,100,98,57,101,99,56,50,51,47,114,101,115,111,108,118,45,99,111,110,102,45,48,46,54,46,50,47,115,114,99,47,99,111,110,102,105,103,46,114,115],"byte_start":19646,"byte_end":19667,"line_start":95,"line_end":95,"column_start":9,"column_end":30},"name":"single_request_reopen","qualname":"::config::Config::single_request_reopen","value":"bool","parent":{"krate":0,"index":294},"children":[],"decl_id":null,"docs":" Use same socket for the A and AAAA requests\n","sig":null,"attributes":[]},{"kind":"Field","id":{"krate":0,"index":177},"span":{"file_name":[47,85,115,101,114,115,47,107,97,102,117,104,97,109,97,100,97,47,46,99,97,114,103,111,47,114,101,103,105,115,116,114,121,47,115,114,99,47,103,105,116,104,117,98,46,99,111,109,45,49,101,99,99,54,50,57,57,100,98,57,101,99,56,50,51,47,114,101,115,111,108,118,45,99,111,110,102,45,48,46,54,46,50,47,115,114,99,47,99,111,110,102,105,103,46,114,115],"byte_start":19742,"byte_end":19754,"line_start":97,"line_end":97,"column_start":9,"column_end":21},"name":"no_tld_query","qualname":"::config::Config::no_tld_query","value":"bool","parent":{"krate":0,"index":294},"children":[],"decl_id":null,"docs":" Don't resolve unqualified name as top level domain\n","sig":null,"attributes":[]},{"kind":"Field","id":{"krate":0,"index":179},"span":{"file_name":[47,85,115,101,114,115,47,107,97,102,117,104,97,109,97,100,97,47,46,99,97,114,103,111,47,114,101,103,105,115,116,114,121,47,115,114,99,47,103,105,116,104,117,98,46,99,111,109,45,49,101,99,99,54,50,57,57,100,98,57,101,99,56,50,51,47,114,101,115,111,108,118,45,99,111,110,102,45,48,46,54,46,50,47,115,114,99,47,99,111,110,102,105,103,46,114,115],"byte_start":19813,"byte_end":19819,"line_start":99,"line_end":99,"column_start":9,"column_end":15},"name":"use_vc","qualname":"::config::Config::use_vc","value":"bool","parent":{"krate":0,"index":294},"children":[],"decl_id":null,"docs":" Force using TCP for DNS resolution\n","sig":null,"attributes":[]},{"kind":"Field","id":{"krate":0,"index":181},"span":{"file_name":[47,85,115,101,114,115,47,107,97,102,117,104,97,109,97,100,97,47,46,99,97,114,103,111,47,114,101,103,105,115,116,114,121,47,115,114,99,47,103,105,116,104,117,98,46,99,111,109,45,49,101,99,99,54,50,57,57,100,98,57,101,99,56,50,51,47,114,101,115,111,108,118,45,99,111,110,102,45,48,46,54,46,50,47,115,114,99,47,99,111,110,102,105,103,46,114,115],"byte_start":19934,"byte_end":19940,"line_start":102,"line_end":102,"column_start":9,"column_end":15},"name":"lookup","qualname":"::config::Config::lookup","value":"std::vec::Vec<config::Lookup>","parent":{"krate":0,"index":294},"children":[],"decl_id":null,"docs":" The order in which databases should be searched during a lookup\n **(openbsd-only)**\n","sig":null,"attributes":[]},{"kind":"Field","id":{"krate":0,"index":183},"span":{"file_name":[47,85,115,101,114,115,47,107,97,102,117,104,97,109,97,100,97,47,46,99,97,114,103,111,47,114,101,103,105,115,116,114,121,47,115,114,99,47,103,105,116,104,117,98,46,99,111,109,45,49,101,99,99,54,50,57,57,100,98,57,101,99,56,50,51,47,114,101,115,111,108,118,45,99,111,110,102,45,48,46,54,46,50,47,115,114,99,47,99,111,110,102,105,103,46,114,115],"byte_start":20063,"byte_end":20069,"line_start":105,"line_end":105,"column_start":9,"column_end":15},"name":"family","qualname":"::config::Config::family","value":"std::vec::Vec<config::Family>","parent":{"krate":0,"index":294},"children":[],"decl_id":null,"docs":" The order in which internet protocol families should be prefered\n **(openbsd-only)**\n","sig":null,"attributes":[]},{"kind":"Method","id":{"krate":0,"index":144},"span":{"file_name":[47,85,115,101,114,115,47,107,97,102,117,104,97,109,97,100,97,47,46,99,97,114,103,111,47,114,101,103,105,115,116,114,121,47,115,114,99,47,103,105,116,104,117,98,46,99,111,109,45,49,101,99,99,54,50,57,57,100,98,57,101,99,56,50,51,47,114,101,115,111,108,118,45,99,111,110,102,45,48,46,54,46,50,47,115,114,99,47,99,111,110,102,105,103,46,114,115],"byte_start":21146,"byte_end":21149,"line_start":135,"line_end":135,"column_start":12,"column_end":15},"name":"new","qualname":"<Config>::new","value":"fn () -> Config","parent":null,"children":[],"decl_id":null,"docs":" Create a new `Config` object with default values.","sig":null,"attributes":[]},{"kind":"Method","id":{"krate":0,"index":146},"span":{"file_name":[47,85,115,101,114,115,47,107,97,102,117,104,97,109,97,100,97,47,46,99,97,114,103,111,47,114,101,103,105,115,116,114,121,47,115,114,99,47,103,105,116,104,117,98,46,99,111,109,45,49,101,99,99,54,50,57,57,100,98,57,101,99,56,50,51,47,114,101,115,111,108,118,45,99,111,110,102,45,48,46,54,46,50,47,115,114,99,47,99,111,110,102,105,103,46,114,115],"byte_start":22465,"byte_end":22470,"line_start":180,"line_end":180,"column_start":12,"column_end":17},"name":"parse","qualname":"<Config>::parse","value":"fn <T> (buf: T) -> Result<Config, ParseError>","parent":null,"children":[],"decl_id":null,"docs":" Parse a buffer and return the corresponding `Config` object.","sig":null,"attributes":[]},{"kind":"Method","id":{"krate":0,"index":148},"span":{"file_name":[47,85,115,101,114,115,47,107,97,102,117,104,97,109,97,100,97,47,46,99,97,114,103,111,47,114,101,103,105,115,116,114,121,47,115,114,99,47,103,105,116,104,117,98,46,99,111,109,45,49,101,99,99,54,50,57,57,100,98,57,101,99,56,50,51,47,114,101,115,111,108,118,45,99,111,110,102,45,48,46,54,46,50,47,115,114,99,47,99,111,110,102,105,103,46,114,115],"byte_start":23697,"byte_end":23722,"line_start":204,"line_end":204,"column_start":12,"column_end":37},"name":"get_last_search_or_domain","qualname":"<Config>::get_last_search_or_domain","value":"fn <'a> (&'a self) -> DomainIter<'a>","parent":null,"children":[],"decl_id":null,"docs":" Return the suffixes declared in the last \"domain\" or \"search\" directive.","sig":null,"attributes":[]},{"kind":"Method","id":{"krate":0,"index":150},"span":{"file_name":[47,85,115,101,114,115,47,107,97,102,117,104,97,109,97,100,97,47,46,99,97,114,103,111,47,114,101,103,105,115,116,114,121,47,115,114,99,47,103,105,116,104,117,98,46,99,111,109,45,49,101,99,99,54,50,57,57,100,98,57,101,99,56,50,51,47,114,101,115,111,108,118,45,99,111,110,102,45,48,46,54,46,50,47,115,114,99,47,99,111,110,102,105,103,46,114,115],"byte_start":24254,"byte_end":24264,"line_start":217,"line_end":217,"column_start":12,"column_end":22},"name":"get_domain","qualname":"<Config>::get_domain","value":"fn (&self) -> Option<&String>","parent":null,"children":[],"decl_id":null,"docs":" Return the domain declared in the last \"domain\" directive.\n","sig":null,"attributes":[]},{"kind":"Method","id":{"krate":0,"index":152},"span":{"file_name":[47,85,115,101,114,115,47,107,97,102,117,104,97,109,97,100,97,47,46,99,97,114,103,111,47,114,101,103,105,115,116,114,121,47,115,114,99,47,103,105,116,104,117,98,46,99,111,109,45,49,101,99,99,54,50,57,57,100,98,57,101,99,56,50,51,47,114,101,115,111,108,118,45,99,111,110,102,45,48,46,54,46,50,47,115,114,99,47,99,111,110,102,105,103,46,114,115],"byte_start":24408,"byte_end":24418,"line_start":222,"line_end":222,"column_start":12,"column_end":22},"name":"get_search","qualname":"<Config>::get_search","value":"fn (&self) -> Option<&Vec<String>>","parent":null,"children":[],"decl_id":null,"docs":" Return the domains declared in the last \"search\" directive.\n","sig":null,"attributes":[]},{"kind":"Method","id":{"krate":0,"index":154},"span":{"file_name":[47,85,115,101,114,115,47,107,97,102,117,104,97,109,97,100,97,47,46,99,97,114,103,111,47,114,101,103,105,115,116,114,121,47,115,114,99,47,103,105,116,104,117,98,46,99,111,109,45,49,101,99,99,54,50,57,57,100,98,57,101,99,56,50,51,47,114,101,115,111,108,118,45,99,111,110,102,45,48,46,54,46,50,47,115,114,99,47,99,111,110,102,105,103,46,114,115],"byte_start":24563,"byte_end":24573,"line_start":227,"line_end":227,"column_start":12,"column_end":22},"name":"set_domain","qualname":"<Config>::set_domain","value":"fn (&mut self, domain: String) -> ()","parent":null,"children":[],"decl_id":null,"docs":" Set the domain corresponding to the \"domain\" directive.\n","sig":null,"attributes":[]},{"kind":"Method","id":{"krate":0,"index":156},"span":{"file_name":[47,85,115,101,114,115,47,107,97,102,117,104,97,109,97,100,97,47,46,99,97,114,103,111,47,114,101,103,105,115,116,114,121,47,115,114,99,47,103,105,116,104,117,98,46,99,111,109,45,49,101,99,99,54,50,57,57,100,98,57,101,99,56,50,51,47,114,101,115,111,108,118,45,99,111,110,102,45,48,46,54,46,50,47,115,114,99,47,99,111,110,102,105,103,46,114,115],"byte_start":24766,"byte_end":24776,"line_start":233,"line_end":233,"column_start":12,"column_end":22},"name":"set_search","qualname":"<Config>::set_search","value":"fn (&mut self, search: Vec<String>) -> ()","parent":null,"children":[],"decl_id":null,"docs":" Set the domains corresponding the \"search\" directive.\n","sig":null,"attributes":[]},{"kind":"Method","id":{"krate":0,"index":158},"span":{"file_name":[47,85,115,101,114,115,47,107,97,102,117,104,97,109,97,100,97,47,46,99,97,114,103,111,47,114,101,103,105,115,116,114,121,47,115,114,99,47,103,105,116,104,117,98,46,99,111,109,45,49,101,99,99,54,50,57,57,100,98,57,101,99,56,50,51,47,114,101,115,111,108,118,45,99,111,110,102,45,48,46,54,46,50,47,115,114,99,47,99,111,110,102,105,103,46,114,115],"byte_start":25506,"byte_end":25521,"line_start":251,"line_end":251,"column_start":12,"column_end":27},"name":"glibc_normalize","qualname":"<Config>::glibc_normalize","value":"fn (&mut self) -> ()","parent":null,"children":[],"decl_id":null,"docs":" Normalize config according to glibc rulees","sig":null,"attributes":[]},{"kind":"Method","id":{"krate":0,"index":160},"span":{"file_name":[47,85,115,101,114,115,47,107,97,102,117,104,97,109,97,100,97,47,46,99,97,114,103,111,47,114,101,103,105,115,116,114,121,47,115,114,99,47,103,105,116,104,117,98,46,99,111,109,45,49,101,99,99,54,50,57,57,100,98,57,101,99,56,50,51,47,114,101,115,111,108,118,45,99,111,110,102,45,48,46,54,46,50,47,115,114,99,47,99,111,110,102,105,103,46,114,115],"byte_start":25772,"byte_end":25796,"line_start":260,"line_end":260,"column_start":12,"column_end":36},"name":"get_nameservers_or_local","qualname":"<Config>::get_nameservers_or_local","value":"fn (&self) -> Vec<ScopedIp>","parent":null,"children":[],"decl_id":null,"docs":" Get nameserver or on the local machine\n","sig":null,"attributes":[]},{"kind":"Method","id":{"krate":0,"index":162},"span":{"file_name":[47,85,115,101,114,115,47,107,97,102,117,104,97,109,97,100,97,47,46,99,97,114,103,111,47,114,101,103,105,115,116,114,121,47,115,114,99,47,103,105,116,104,117,98,46,99,111,109,45,49,101,99,99,54,50,57,57,100,98,57,101,99,56,50,51,47,114,101,115,111,108,118,45,99,111,110,102,45,48,46,54,46,50,47,115,114,99,47,99,111,110,102,105,103,46,114,115],"byte_start":26350,"byte_end":26367,"line_start":276,"line_end":276,"column_start":12,"column_end":29},"name":"get_system_domain","qualname":"<Config>::get_system_domain","value":"fn (&self) -> Option<String>","parent":null,"children":[],"decl_id":null,"docs":" Get domain from config or fallback to the suffix of a hostname","sig":null,"attributes":[{"value":"cfg(feature = \"system\")","span":{"file_name":[47,85,115,101,114,115,47,107,97,102,117,104,97,109,97,100,97,47,46,99,97,114,103,111,47,114,101,103,105,115,116,114,121,47,115,114,99,47,103,105,116,104,117,98,46,99,111,109,45,49,101,99,99,54,50,57,57,100,98,57,101,99,56,50,51,47,114,101,115,111,108,118,45,99,111,110,102,45,48,46,54,46,50,47,115,114,99,47,99,111,110,102,105,103,46,114,115],"byte_start":26312,"byte_end":26338,"line_start":275,"line_end":275,"column_start":5,"column_end":31}}]},{"kind":"Struct","id":{"krate":0,"index":314},"span":{"file_name":[47,85,115,101,114,115,47,107,97,102,117,104,97,109,97,100,97,47,46,99,97,114,103,111,47,114,101,103,105,115,116,114,121,47,115,114,99,47,103,105,116,104,117,98,46,99,111,109,45,49,101,99,99,54,50,57,57,100,98,57,101,99,56,50,51,47,114,101,115,111,108,118,45,99,111,110,102,45,48,46,54,46,50,47,115,114,99,47,99,111,110,102,105,103,46,114,115],"byte_start":29334,"byte_end":29344,"line_start":378,"line_end":378,"column_start":12,"column_end":22},"name":"DomainIter","qualname":"::config::DomainIter","value":"","parent":null,"children":[],"decl_id":null,"docs":" An iterator returned by [`Config.get_last_search_or_domain`](struct.Config.html#method.get_last_search_or_domain)\n","sig":null,"attributes":[]},{"kind":"TupleVariant","id":{"krate":0,"index":211},"span":{"file_name":[47,85,115,101,114,115,47,107,97,102,117,104,97,109,97,100,97,47,46,99,97,114,103,111,47,114,101,103,105,115,116,114,121,47,115,114,99,47,103,105,116,104,117,98,46,99,111,109,45,49,101,99,99,54,50,57,57,100,98,57,101,99,56,50,51,47,114,101,115,111,108,118,45,99,111,110,102,45,48,46,54,46,50,47,115,114,99,47,99,111,110,102,105,103,46,114,115],"byte_start":30206,"byte_end":30210,"line_start":412,"line_end":412,"column_start":5,"column_end":9},"name":"File","qualname":"::config::Lookup::File","value":"Lookup::File","parent":{"krate":0,"index":334},"children":[],"decl_id":null,"docs":" Search for entries in /etc/hosts\n","sig":null,"attributes":[]},{"kind":"TupleVariant","id":{"krate":0,"index":213},"span":{"file_name":[47,85,115,101,114,115,47,107,97,102,117,104,97,109,97,100,97,47,46,99,97,114,103,111,47,114,101,103,105,115,116,114,121,47,115,114,99,47,103,105,116,104,117,98,46,99,111,109,45,49,101,99,99,54,50,57,57,100,98,57,101,99,56,50,51,47,114,101,115,111,108,118,45,99,111,110,102,45,48,46,54,46,50,47,115,114,99,47,99,111,110,102,105,103,46,114,115],"byte_start":30251,"byte_end":30255,"line_start":414,"line_end":414,"column_start":5,"column_end":9},"name":"Bind","qualname":"::config::Lookup::Bind","value":"Lookup::Bind","parent":{"krate":0,"index":334},"children":[],"decl_id":null,"docs":" Query a domain name server\n","sig":null,"attributes":[]},{"kind":"TupleVariant","id":{"krate":0,"index":215},"span":{"file_name":[47,85,115,101,114,115,47,107,97,102,117,104,97,109,97,100,97,47,46,99,97,114,103,111,47,114,101,103,105,115,116,114,121,47,115,114,99,47,103,105,116,104,117,98,46,99,111,109,45,49,101,99,99,54,50,57,57,100,98,57,101,99,56,50,51,47,114,101,115,111,108,118,45,99,111,110,102,45,48,46,54,46,50,47,115,114,99,47,99,111,110,102,105,103,46,114,115],"byte_start":30298,"byte_end":30303,"line_start":416,"line_end":416,"column_start":5,"column_end":10},"name":"Extra","qualname":"::config::Lookup::Extra","value":"Lookup::Extra(String)","parent":{"krate":0,"index":334},"children":[],"decl_id":null,"docs":" A database we don't know yet\n","sig":null,"attributes":[]},{"kind":"Enum","id":{"krate":0,"index":334},"span":{"file_name":[47,85,115,101,114,115,47,107,97,102,117,104,97,109,97,100,97,47,46,99,97,114,103,111,47,114,101,103,105,115,116,114,121,47,115,114,99,47,103,105,116,104,117,98,46,99,111,109,45,49,101,99,99,54,50,57,57,100,98,57,101,99,56,50,51,47,114,101,115,111,108,118,45,99,111,110,102,45,48,46,54,46,50,47,115,114,99,47,99,111,110,102,105,103,46,114,115],"byte_start":30152,"byte_end":30158,"line_start":410,"line_end":410,"column_start":10,"column_end":16},"name":"Lookup","qualname":"::config::Lookup","value":"Lookup::{File, Bind, Extra}","parent":null,"children":[{"krate":0,"index":211},{"krate":0,"index":213},{"krate":0,"index":215}],"decl_id":null,"docs":" The databases that should be searched during a lookup.\n This option is commonly found on openbsd.\n","sig":null,"attributes":[{"value":"structural_match","span":{"file_name":[47,85,115,101,114,115,47,107,97,102,117,104,97,109,97,100,97,47,46,99,97,114,103,111,47,114,101,103,105,115,116,114,121,47,115,114,99,47,103,105,116,104,117,98,46,99,111,109,45,49,101,99,99,54,50,57,57,100,98,57,101,99,56,50,51,47,114,101,115,111,108,118,45,99,111,110,102,45,48,46,54,46,50,47,115,114,99,47,99,111,110,102,105,103,46,114,115],"byte_start":30143,"byte_end":30314,"line_start":410,"line_end":417,"column_start":1,"column_end":2}}]},{"kind":"TupleVariant","id":{"krate":0,"index":219},"span":{"file_name":[47,85,115,101,114,115,47,107,97,102,117,104,97,109,97,100,97,47,46,99,97,114,103,111,47,114,101,103,105,115,116,114,121,47,115,114,99,47,103,105,116,104,117,98,46,99,111,109,45,49,101,99,99,54,50,57,57,100,98,57,101,99,56,50,51,47,114,101,115,111,108,118,45,99,111,110,102,45,48,46,54,46,50,47,115,114,99,47,99,111,110,102,105,103,46,114,115],"byte_start":30513,"byte_end":30518,"line_start":424,"line_end":424,"column_start":5,"column_end":10},"name":"Inet4","qualname":"::config::Family::Inet4","value":"Family::Inet4","parent":{"krate":0,"index":354},"children":[],"decl_id":null,"docs":" A A lookup for an ipv4 address\n","sig":null,"attributes":[]},{"kind":"TupleVariant","id":{"krate":0,"index":221},"span":{"file_name":[47,85,115,101,114,115,47,107,97,102,117,104,97,109,97,100,97,47,46,99,97,114,103,111,47,114,101,103,105,115,116,114,121,47,115,114,99,47,103,105,116,104,117,98,46,99,111,109,45,49,101,99,99,54,50,57,57,100,98,57,101,99,56,50,51,47,114,101,115,111,108,118,45,99,111,110,102,45,48,46,54,46,50,47,115,114,99,47,99,111,110,102,105,103,46,114,115],"byte_start":30566,"byte_end":30571,"line_start":426,"line_end":426,"column_start":5,"column_end":10},"name":"Inet6","qualname":"::config::Family::Inet6","value":"Family::Inet6","parent":{"krate":0,"index":354},"children":[],"decl_id":null,"docs":" A AAAA lookup for an ipv6 address\n","sig":null,"attributes":[]},{"kind":"Enum","id":{"krate":0,"index":354},"span":{"file_name":[47,85,115,101,114,115,47,107,97,102,117,104,97,109,97,100,97,47,46,99,97,114,103,111,47,114,101,103,105,115,116,114,121,47,115,114,99,47,103,105,116,104,117,98,46,99,111,109,45,49,101,99,99,54,50,57,57,100,98,57,101,99,56,50,51,47,114,101,115,111,108,118,45,99,111,110,102,45,48,46,54,46,50,47,115,114,99,47,99,111,110,102,105,103,46,114,115],"byte_start":30461,"byte_end":30467,"line_start":422,"line_end":422,"column_start":10,"column_end":16},"name":"Family","qualname":"::config::Family","value":"Family::{Inet4, Inet6}","parent":null,"children":[{"krate":0,"index":219},{"krate":0,"index":221}],"decl_id":null,"docs":" The internet protocol family that is prefered.\n This option is commonly found on openbsd.\n","sig":null,"attributes":[{"value":"structural_match","span":{"file_name":[47,85,115,101,114,115,47,107,97,102,117,104,97,109,97,100,97,47,46,99,97,114,103,111,47,114,101,103,105,115,116,114,121,47,115,114,99,47,103,105,116,104,117,98,46,99,111,109,45,49,101,99,99,54,50,57,57,100,98,57,101,99,56,50,51,47,114,101,115,111,108,118,45,99,111,110,102,45,48,46,54,46,50,47,115,114,99,47,99,111,110,102,105,103,46,114,115],"byte_start":30452,"byte_end":30574,"line_start":422,"line_end":427,"column_start":1,"column_end":2}}]}],"impls":[{"id":0,"kind":"Direct","span":{"file_name":[47,85,115,101,114,115,47,107,97,102,117,104,97,109,97,100,97,47,46,99,97,114,103,111,47,114,101,103,105,115,116,114,121,47,115,114,99,47,103,105,116,104,117,98,46,99,111,109,45,49,101,99,99,54,50,57,57,100,98,57,101,99,56,50,51,47,114,101,115,111,108,118,45,99,111,110,102,45,48,46,54,46,50,47,115,114,99,47,105,112,46,114,115],"byte_start":12653,"byte_end":12660,"line_start":15,"line_end":15,"column_start":23,"column_end":30},"value":"","parent":null,"children":[{"krate":0,"index":62}],"docs":"","sig":null,"attributes":[]},{"id":1,"kind":"Direct","span":{"file_name":[47,85,115,101,114,115,47,107,97,102,117,104,97,109,97,100,97,47,46,99,97,114,103,111,47,114,101,103,105,115,116,114,121,47,115,114,99,47,103,105,116,104,117,98,46,99,111,109,45,49,101,99,99,54,50,57,57,100,98,57,101,99,56,50,51,47,114,101,115,111,108,118,45,99,111,110,102,45,48,46,54,46,50,47,115,114,99,47,105,112,46,114,115],"byte_start":13268,"byte_end":13276,"line_start":34,"line_end":34,"column_start":23,"column_end":31},"value":"","parent":null,"children":[{"krate":0,"index":66}],"docs":"","sig":null,"attributes":[]},{"id":2,"kind":"Direct","span":{"file_name":[47,85,115,101,114,115,47,107,97,102,117,104,97,109,97,100,97,47,46,99,97,114,103,111,47,114,101,103,105,115,116,114,121,47,115,114,99,47,103,105,116,104,117,98,46,99,111,109,45,49,101,99,99,54,50,57,57,100,98,57,101,99,56,50,51,47,114,101,115,111,108,118,45,99,111,110,102,45,48,46,54,46,50,47,115,114,99,47,105,112,46,114,115],"byte_start":13701,"byte_end":13709,"line_start":52,"line_end":52,"column_start":25,"column_end":33},"value":"","parent":null,"children":[{"krate":0,"index":74}],"docs":"","sig":null,"attributes":[]},{"id":3,"kind":"Direct","span":{"file_name":[47,85,115,101,114,115,47,107,97,102,117,104,97,109,97,100,97,47,46,99,97,114,103,111,47,114,101,103,105,115,116,114,121,47,115,114,99,47,103,105,116,104,117,98,46,99,111,109,45,49,101,99,99,54,50,57,57,100,98,57,101,99,56,50,51,47,114,101,115,111,108,118,45,99,111,110,102,45,48,46,54,46,50,47,115,114,99,47,105,112,46,114,115],"byte_start":13818,"byte_end":13826,"line_start":58,"line_end":58,"column_start":25,"column_end":33},"value":"","parent":null,"children":[{"krate":0,"index":78}],"docs":"","sig":null,"attributes":[]},{"id":4,"kind":"Direct","span":{"file_name":[47,85,115,101,114,115,47,107,97,102,117,104,97,109,97,100,97,47,46,99,97,114,103,111,47,114,101,103,105,115,116,114,121,47,115,114,99,47,103,105,116,104,117,98,46,99,111,109,45,49,101,99,99,54,50,57,57,100,98,57,101,99,56,50,51,47,114,101,115,111,108,118,45,99,111,110,102,45,48,46,54,46,50,47,115,114,99,47,105,112,46,114,115],"byte_start":13927,"byte_end":13935,"line_start":64,"line_end":64,"column_start":23,"column_end":31},"value":"","parent":null,"children":[{"krate":0,"index":82}],"docs":"","sig":null,"attributes":[]},{"id":5,"kind":"Direct","span":{"file_name":[47,85,115,101,114,115,47,107,97,102,117,104,97,109,97,100,97,47,46,99,97,114,103,111,47,114,101,103,105,115,116,114,121,47,115,114,99,47,103,105,116,104,117,98,46,99,111,109,45,49,101,99,99,54,50,57,57,100,98,57,101,99,56,50,51,47,114,101,115,111,108,118,45,99,111,110,102,45,48,46,54,46,50,47,115,114,99,47,105,112,46,114,115],"byte_start":14133,"byte_end":14141,"line_start":73,"line_end":73,"column_start":18,"column_end":26},"value":"","parent":null,"children":[{"krate":0,"index":86},{"krate":0,"index":88}],"docs":"","sig":null,"attributes":[]},{"id":6,"kind":"Direct","span":{"file_name":[47,85,115,101,114,115,47,107,97,102,117,104,97,109,97,100,97,47,46,99,97,114,103,111,47,114,101,103,105,115,116,114,121,47,115,114,99,47,103,105,116,104,117,98,46,99,111,109,45,49,101,99,99,54,50,57,57,100,98,57,101,99,56,50,51,47,114,101,115,111,108,118,45,99,111,110,102,45,48,46,54,46,50,47,115,114,99,47,105,112,46,114,115],"byte_start":15286,"byte_end":15294,"line_start":106,"line_end":106,"column_start":23,"column_end":31},"value":"","parent":null,"children":[{"krate":0,"index":92}],"docs":"","sig":null,"attributes":[]},{"id":7,"kind":"Direct","span":{"file_name":[47,85,115,101,114,115,47,107,97,102,117,104,97,109,97,100,97,47,46,99,97,114,103,111,47,114,101,103,105,115,116,114,121,47,115,114,99,47,103,105,116,104,117,98,46,99,111,109,45,49,101,99,99,54,50,57,57,100,98,57,101,99,56,50,51,47,114,101,115,111,108,118,45,99,111,110,102,45,48,46,54,46,50,47,115,114,99,47,105,112,46,114,115],"byte_start":15771,"byte_end":15785,"line_start":120,"line_end":120,"column_start":23,"column_end":37},"value":"","parent":null,"children":[{"krate":0,"index":96}],"docs":"","sig":null,"attributes":[]},{"id":8,"kind":"Direct","span":{"file_name":[47,85,115,101,114,115,47,107,97,102,117,104,97,109,97,100,97,47,46,99,97,114,103,111,47,114,101,103,105,115,116,114,121,47,115,114,99,47,103,105,116,104,117,98,46,99,111,109,45,49,101,99,99,54,50,57,57,100,98,57,101,99,56,50,51,47,114,101,115,111,108,118,45,99,111,110,102,45,48,46,54,46,50,47,115,114,99,47,105,112,46,114,115],"byte_start":15915,"byte_end":15929,"line_start":126,"line_end":126,"column_start":16,"column_end":30},"value":"","parent":null,"children":[{"krate":0,"index":100}],"docs":"","sig":null,"attributes":[]},{"id":9,"kind":"Direct","span":{"file_name":[47,85,115,101,114,115,47,107,97,102,117,104,97,109,97,100,97,47,46,99,97,114,103,111,47,114,101,103,105,115,116,114,121,47,115,114,99,47,103,105,116,104,117,98,46,99,111,109,45,49,101,99,99,54,50,57,57,100,98,57,101,99,56,50,51,47,114,101,115,111,108,118,45,99,111,110,102,45,48,46,54,46,50,47,115,114,99,47,105,112,46,114,115],"byte_start":16055,"byte_end":16069,"line_start":132,"line_end":132,"column_start":43,"column_end":57},"value":"","parent":null,"children":[{"krate":0,"index":104}],"docs":"","sig":null,"attributes":[]},{"id":10,"kind":"Inherent","span":{"file_name":[47,85,115,101,114,115,47,107,97,102,117,104,97,109,97,100,97,47,46,99,97,114,103,111,47,114,101,103,105,115,116,114,121,47,115,114,99,47,103,105,116,104,117,98,46,99,111,109,45,49,101,99,99,54,50,57,57,100,98,57,101,99,56,50,51,47,114,101,115,111,108,118,45,99,111,110,102,45,48,46,54,46,50,47,115,114,99,47,99,111,110,102,105,103,46,114,115],"byte_start":20092,"byte_end":20098,"line_start":108,"line_end":108,"column_start":6,"column_end":12},"value":"","parent":null,"children":[{"krate":0,"index":144},{"krate":0,"index":146},{"krate":0,"index":148},{"krate":0,"index":150},{"krate":0,"index":152},{"krate":0,"index":154},{"krate":0,"index":156},{"krate":0,"index":158},{"krate":0,"index":160},{"krate":0,"index":162}],"docs":"","sig":null,"attributes":[]},{"id":11,"kind":"Direct","span":{"file_name":[47,85,115,101,114,115,47,107,97,102,117,104,97,109,97,100,97,47,46,99,97,114,103,111,47,114,101,103,105,115,116,114,121,47,115,114,99,47,103,105,116,104,117,98,46,99,111,109,45,49,101,99,99,54,50,57,57,100,98,57,101,99,56,50,51,47,114,101,115,111,108,118,45,99,111,110,102,45,48,46,54,46,50,47,115,114,99,47,99,111,110,102,105,103,46,114,115],"byte_start":26787,"byte_end":26793,"line_start":293,"line_end":293,"column_start":23,"column_end":29},"value":"","parent":null,"children":[{"krate":0,"index":166}],"docs":"","sig":null,"attributes":[]},{"id":12,"kind":"Direct","span":{"file_name":[47,85,115,101,114,115,47,107,97,102,117,104,97,109,97,100,97,47,46,99,97,114,103,111,47,114,101,103,105,115,116,114,121,47,115,114,99,47,103,105,116,104,117,98,46,99,111,109,45,49,101,99,99,54,50,57,57,100,98,57,101,99,56,50,51,47,114,101,115,111,108,118,45,99,111,110,102,45,48,46,54,46,50,47,115,114,99,47,99,111,110,102,105,103,46,114,115],"byte_start":29397,"byte_end":29407,"line_start":380,"line_end":380,"column_start":23,"column_end":33},"value":"","parent":null,"children":[{"krate":0,"index":170},{"krate":0,"index":172}],"docs":"","sig":null,"attributes":[]},{"id":13,"kind":"Direct","span":{"file_name":[47,85,115,101,114,115,47,107,97,102,117,104,97,109,97,100,97,47,46,99,97,114,103,111,47,114,101,103,105,115,116,114,121,47,115,114,99,47,103,105,116,104,117,98,46,99,111,109,45,49,101,99,99,54,50,57,57,100,98,57,101,99,56,50,51,47,114,101,115,111,108,118,45,99,111,110,102,45,48,46,54,46,50,47,115,114,99,47,99,111,110,102,105,103,46,114,115],"byte_start":29680,"byte_end":29698,"line_start":395,"line_end":395,"column_start":23,"column_end":41},"value":"","parent":null,"children":[{"krate":0,"index":176},{"krate":0,"index":178}],"docs":"","sig":null,"attributes":[]}],"refs":[],"macro_refs":[],"relations":[{"span":{"file_name":[47,85,115,101,114,115,47,107,97,102,117,104,97,109,97,100,97,47,46,99,97,114,103,111,47,114,101,103,105,115,116,114,121,47,115,114,99,47,103,105,116,104,117,98,46,99,111,109,45,49,101,99,99,54,50,57,57,100,98,57,101,99,56,50,51,47,114,101,115,111,108,118,45,99,111,110,102,45,48,46,54,46,50,47,115,114,99,47,105,112,46,114,115],"byte_start":12653,"byte_end":12660,"line_start":15,"line_end":15,"column_start":23,"column_end":30},"kind":{"variant":"Impl","fields":[0]},"from":{"krate":0,"index":216},"to":{"krate":2,"index":8430}},{"span":{"file_name":[47,85,115,101,114,115,47,107,97,102,117,104,97,109,97,100,97,47,46,99,97,114,103,111,47,114,101,103,105,115,116,114,121,47,115,114,99,47,103,105,116,104,117,98,46,99,111,109,45,49,101,99,99,54,50,57,57,100,98,57,101,99,56,50,51,47,114,101,115,111,108,118,45,99,111,110,102,45,48,46,54,46,50,47,115,114,99,47,105,112,46,114,115],"byte_start":13268,"byte_end":13276,"line_start":34,"line_end":34,"column_start":23,"column_end":31},"kind":{"variant":"Impl","fields":[1]},"from":{"krate":0,"index":236},"to":{"krate":2,"index":2652}},{"span":{"file_name":[47,85,115,101,114,115,47,107,97,102,117,104,97,109,97,100,97,47,46,99,97,114,103,111,47,114,101,103,105,115,116,114,121,47,115,114,99,47,103,105,116,104,117,98,46,99,111,109,45,49,101,99,99,54,50,57,57,100,98,57,101,99,56,50,51,47,114,101,115,111,108,118,45,99,111,110,102,45,48,46,54,46,50,47,115,114,99,47,105,112,46,114,115],"byte_start":13701,"byte_end":13709,"line_start":52,"line_end":52,"column_start":25,"column_end":33},"kind":{"variant":"Impl","fields":[2]},"from":{"krate":0,"index":236},"to":{"krate":2,"index":2656}},{"span":{"file_name":[47,85,115,101,114,115,47,107,97,102,117,104,97,109,97,100,97,47,46,99,97,114,103,111,47,114,101,103,105,115,116,114,121,47,115,114,99,47,103,105,116,104,117,98,46,99,111,109,45,49,101,99,99,54,50,57,57,100,98,57,101,99,56,50,51,47,114,101,115,111,108,118,45,99,111,110,102,45,48,46,54,46,50,47,115,114,99,47,105,112,46,114,115],"byte_start":13818,"byte_end":13826,"line_start":58,"line_end":58,"column_start":25,"column_end":33},"kind":{"variant":"Impl","fields":[3]},"from":{"krate":0,"index":236},"to":{"krate":2,"index":2656}},{"span":{"file_name":[47,85,115,101,114,115,47,107,97,102,117,104,97,109,97,100,97,47,46,99,97,114,103,111,47,114,101,103,105,115,116,114,121,47,115,114,99,47,103,105,116,104,117,98,46,99,111,109,45,49,101,99,99,54,50,57,57,100,98,57,101,99,56,50,51,47,114,101,115,111,108,118,45,99,111,110,102,45,48,46,54,46,50,47,115,114,99,47,105,112,46,114,115],"byte_start":13927,"byte_end":13935,"line_start":64,"line_end":64,"column_start":23,"column_end":31},"kind":{"variant":"Impl","fields":[4]},"from":{"krate":0,"index":236},"to":{"krate":2,"index":2656}},{"span":{"file_name":[47,85,115,101,114,115,47,107,97,102,117,104,97,109,97,100,97,47,46,99,97,114,103,111,47,114,101,103,105,115,116,114,121,47,115,114,99,47,103,105,116,104,117,98,46,99,111,109,45,49,101,99,99,54,50,57,57,100,98,57,101,99,56,50,51,47,114,101,115,111,108,118,45,99,111,110,102,45,48,46,54,46,50,47,115,114,99,47,105,112,46,114,115],"byte_start":14133,"byte_end":14141,"line_start":73,"line_end":73,"column_start":18,"column_end":26},"kind":{"variant":"Impl","fields":[5]},"from":{"krate":0,"index":236},"to":{"krate":2,"index":7356}},{"span":{"file_name":[47,85,115,101,114,115,47,107,97,102,117,104,97,109,97,100,97,47,46,99,97,114,103,111,47,114,101,103,105,115,116,114,121,47,115,114,99,47,103,105,116,104,117,98,46,99,111,109,45,49,101,99,99,54,50,57,57,100,98,57,101,99,56,50,51,47,114,101,115,111,108,118,45,99,111,110,102,45,48,46,54,46,50,47,115,114,99,47,105,112,46,114,115],"byte_start":15286,"byte_end":15294,"line_start":106,"line_end":106,"column_start":23,"column_end":31},"kind":{"variant":"Impl","fields":[6]},"from":{"krate":0,"index":236},"to":{"krate":2,"index":8430}},{"span":{"file_name":[47,85,115,101,114,115,47,107,97,102,117,104,97,109,97,100,97,47,46,99,97,114,103,111,47,114,101,103,105,115,116,114,121,47,115,114,99,47,103,105,116,104,117,98,46,99,111,109,45,49,101,99,99,54,50,57,57,100,98,57,101,99,56,50,51,47,114,101,115,111,108,118,45,99,111,110,102,45,48,46,54,46,50,47,115,114,99,47,105,112,46,114,115],"byte_start":15771,"byte_end":15785,"line_start":120,"line_end":120,"column_start":23,"column_end":37},"kind":{"variant":"Impl","fields":[7]},"from":{"krate":0,"index":256},"to":{"krate":2,"index":8430}},{"span":{"file_name":[47,85,115,101,114,115,47,107,97,102,117,104,97,109,97,100,97,47,46,99,97,114,103,111,47,114,101,103,105,115,116,114,121,47,115,114,99,47,103,105,116,104,117,98,46,99,111,109,45,49,101,99,99,54,50,57,57,100,98,57,101,99,56,50,51,47,114,101,115,111,108,118,45,99,111,110,102,45,48,46,54,46,50,47,115,114,99,47,105,112,46,114,115],"byte_start":15915,"byte_end":15929,"line_start":126,"line_end":126,"column_start":16,"column_end":30},"kind":{"variant":"Impl","fields":[8]},"from":{"krate":0,"index":256},"to":{"krate":1,"index":2470}},{"span":{"file_name":[47,85,115,101,114,115,47,107,97,102,117,104,97,109,97,100,97,47,46,99,97,114,103,111,47,114,101,103,105,115,116,114,121,47,115,114,99,47,103,105,116,104,117,98,46,99,111,109,45,49,101,99,99,54,50,57,57,100,98,57,101,99,56,50,51,47,114,101,115,111,108,118,45,99,111,110,102,45,48,46,54,46,50,47,115,114,99,47,105,112,46,114,115],"byte_start":16055,"byte_end":16069,"line_start":132,"line_end":132,"column_start":43,"column_end":57},"kind":{"variant":"Impl","fields":[9]},"from":{"krate":0,"index":256},"to":{"krate":2,"index":2656}},{"span":{"file_name":[47,85,115,101,114,115,47,107,97,102,117,104,97,109,97,100,97,47,46,99,97,114,103,111,47,114,101,103,105,115,116,114,121,47,115,114,99,47,103,105,116,104,117,98,46,99,111,109,45,49,101,99,99,54,50,57,57,100,98,57,101,99,56,50,51,47,114,101,115,111,108,118,45,99,111,110,102,45,48,46,54,46,50,47,115,114,99,47,99,111,110,102,105,103,46,114,115],"byte_start":20092,"byte_end":20098,"line_start":108,"line_end":108,"column_start":6,"column_end":12},"kind":{"variant":"Impl","fields":[10]},"from":{"krate":0,"index":294},"to":{"krate":4294967295,"index":4294967295}},{"span":{"file_name":[47,85,115,101,114,115,47,107,97,102,117,104,97,109,97,100,97,47,46,99,97,114,103,111,47,114,101,103,105,115,116,114,121,47,115,114,99,47,103,105,116,104,117,98,46,99,111,109,45,49,101,99,99,54,50,57,57,100,98,57,101,99,56,50,51,47,114,101,115,111,108,118,45,99,111,110,102,45,48,46,54,46,50,47,115,114,99,47,99,111,110,102,105,103,46,114,115],"byte_start":26787,"byte_end":26793,"line_start":293,"line_end":293,"column_start":23,"column_end":29},"kind":{"variant":"Impl","fields":[11]},"from":{"krate":0,"index":294},"to":{"krate":2,"index":8430}},{"span":{"file_name":[47,85,115,101,114,115,47,107,97,102,117,104,97,109,97,100,97,47,46,99,97,114,103,111,47,114,101,103,105,115,116,114,121,47,115,114,99,47,103,105,116,104,117,98,46,99,111,109,45,49,101,99,99,54,50,57,57,100,98,57,101,99,56,50,51,47,114,101,115,111,108,118,45,99,111,110,102,45,48,46,54,46,50,47,115,114,99,47,99,111,110,102,105,103,46,114,115],"byte_start":29397,"byte_end":29407,"line_start":380,"line_end":380,"column_start":23,"column_end":33},"kind":{"variant":"Impl","fields":[12]},"from":{"krate":0,"index":314},"to":{"krate":2,"index":4316}},{"span":{"file_name":[47,85,115,101,114,115,47,107,97,102,117,104,97,109,97,100,97,47,46,99,97,114,103,111,47,114,101,103,105,115,116,114,121,47,115,114,99,47,103,105,116,104,117,98,46,99,111,109,45,49,101,99,99,54,50,57,57,100,98,57,101,99,56,50,51,47,114,101,115,111,108,118,45,99,111,110,102,45,48,46,54,46,50,47,115,114,99,47,99,111,110,102,105,103,46,114,115],"byte_start":29680,"byte_end":29698,"line_start":395,"line_end":395,"column_start":23,"column_end":41},"kind":{"variant":"Impl","fields":[13]},"from":{"krate":0,"index":324},"to":{"krate":2,"index":4316}}]}